LICENSE
README.md
setup.py
bin/fce
fce/fce.py
fce/fce_datasets.py
fce/fit.py
fce/objects.py
fce/plot.py
fce/rundefault.py
fce.egg-info/PKG-INFO
fce.egg-info/SOURCES.txt
fce.egg-info/dependency_links.txt
fce.egg-info/entry_points.txt
fce.egg-info/requires.txt
fce.egg-info/top_level.txt
fce/config/analysis.dat
fce/config/samples.json
fce/config/selection.dat
fce/config/skim.dat
fce/data/fce.ico