Metadata-Version: 2.1
Name: fce
Version: 0.0.6
Summary: Future Collider Experiment
Home-page: https://github.com/kskovpen/FCE
Author: Kirill Skovpen
Author-email: kirill.skovpen@ugent.be
License: LGPL-2.1
Classifier: Intended Audience :: Science/Research
Classifier: License :: OSI Approved :: GNU Lesser General Public License v2 or later (LGPLv2+)
Classifier: Operating System :: OS Independent
Classifier: Programming Language :: Python :: 3
Requires-Python: >=3.8
License-File: LICENSE
Requires-Dist: PyQt6
Requires-Dist: boost_histogram
Requires-Dist: uproot
Requires-Dist: matplotlib
Requires-Dist: mplhep
Requires-Dist: pyhf
Requires-Dist: cabinetry
Requires-Dist: vector
Requires-Dist: pandas
